{"is_source_file": true, "format": "JavaScript (JSX)", "description": "This file is the entry point of a React application, setting up the root rendering and routing for the app.", "external_files": ["react", "react-dom/client", "./index.css", "./App", "react-router-dom"], "external_methods": ["ReactDOM.createRoot", "root.render"], "published": [], "classes": [], "methods": [{"name": "ReactDOM.createRoot", "description": "Creates a root for rendering React elements in a specified DOM node."}, {"name": "root.render", "description": "Renders React elements into the root."}], "calls": ["ReactDOM.createRoot", "root.render", "<React.StrictMode>", "<BrowserRouter>", "<App />"], "search-terms": ["React", "ReactDOM", "index.js", "entry point", "routing", "React.StrictMode", "App component"], "state": 2, "file_id": 6, "knowledge_revision": 30, "git_revision": "607e75bad462bcc4724f055223bb435438d46d23", "revision_history": [{"23": "607e75bad462bcc4724f055223bb435438d46d23"}, {"30": "607e75bad462bcc4724f055223bb435438d46d23"}], "ctags": [{"_type": "tag", "name": "root", "path": "/home/kavia/workspace/code-generation/connectmatch-184374-184383/dating_app_frontend/src/index.js", "pattern": "/^const root = ReactDOM.createRoot(document.getElementById('root'));$/", "language": "JavaScript", "kind": "constant"}], "hash": "f86d14bc893c29a62bb876420c1f0a76", "format-version": 4, "code-base-name": "dating_app_frontend", "filename": "dating_app_frontend/src/index.js"}